LICENSE
ulinkme/__init__.py
ulinkme/config.py
ulinkme/handlers/__init__.py
ulinkme/handlers/hardlink_handler.py
ulinkme/main.py
ulinkme-0.1.0.dist-info/entry_points.txt
ulinkme-0.1.0.dist-info/LICENSE
ulinkme-0.1.0.dist-info/WHEEL
ulinkme-0.1.0.dist-info/METADATA
ulinkme-0.1.0.dist-info/RECORD
