Metadata-Version: 2.1
Name: ulinkme
Version: 0.1.0
Summary: A cross-platform tool for automatically creating hard links recursively in real time for all files in a given folder.
Home-page: https://github.com/Hyiker/ULinkMe
License: MIT
Keywords: watchdog,link,cli
Author: Hyiker
Author-email: hyikerhu0212@gmail.com
Requires-Python: >=3.9,<4.0
Classifier: License :: OSI Approved :: MIT License
Classifier: Programming Language :: Python :: 3
Classifier: Programming Language :: Python :: 3.10
Classifier: Programming Language :: Python :: 3.9
Requires-Dist: watchdog (>=2.1.9,<3.0.0)
Project-URL: Repository, https://github.com/Hyiker/ULinkMe
